{"Queen":{"username":"LunixScript","total":2182,"inv_value":2094838,"last_updated":"2025-12-13T23:02:57Z","data":[{"name":"Tricolore Butterfly","amount":1796},{"name":"Moorish Idol","amount":6},{"name":"Candy Butterfly","amount":67},{"name":"Sharp One","amount":5},{"name":"Vintage Damsel","amount":165},{"name":"Viperfish","amount":1},{"name":"Ruby","amount":2},{"name":"Blob Shark","amount":2},{"name":"Diamond Ring","amount":3},{"name":"Block Fish","amount":7},{"name":"Jellyfish","amount":3},{"name":"Liar Nose Fish","amount":4},{"name":"Orca","amount":1},{"name":"Sea Shell","amount":2},{"name":"Chrome Tuna","amount":2},{"name":"Cute Octopus","amount":22},{"name":"Traffic Cone Fish","amount":9},{"name":"Blob Fish","amount":11},{"name":"Giant Squid","amount":1},{"name":"Curious Garfish","amount":1},{"name":"Narwhal","amount":7},{"name":"Conch Shell","amount":2},{"name":"Cryoshade Glider","amount":1},{"name":"Expensive Chain","amount":9},{"name":"Cow Clownfish","amount":7},{"name":"Manta Ray","amount":5},{"name":"Dotted Stingray","amount":5},{"name":"Armor Catfish","amount":5},{"name":"Jewel Tang","amount":31}],"balance":8620000}}